odoo/addons/iap_alternative_provider/README.rst
odoo/addons/iap_alternative_provider/__init__.py
odoo/addons/iap_alternative_provider/__manifest__.py
odoo/addons/iap_alternative_provider/i18n/ca.po
odoo/addons/iap_alternative_provider/i18n/iap_alternative_provider.pot
odoo/addons/iap_alternative_provider/i18n/it.po
odoo/addons/iap_alternative_provider/models/__init__.py
odoo/addons/iap_alternative_provider/models/iap_account.py
odoo/addons/iap_alternative_provider/readme/CONTRIBUTORS.rst
odoo/addons/iap_alternative_provider/readme/DESCRIPTION.rst
odoo/addons/iap_alternative_provider/static/description/icon.png
odoo/addons/iap_alternative_provider/static/description/index.html
odoo/addons/iap_alternative_provider/views/iap_account_view.xml
odoo14_addon_iap_alternative_provider-14.0.1.0.1.dev6.dist-info/METADATA
odoo14_addon_iap_alternative_provider-14.0.1.0.1.dev6.dist-info/WHEEL
odoo14_addon_iap_alternative_provider-14.0.1.0.1.dev6.dist-info/top_level.txt
odoo14_addon_iap_alternative_provider-14.0.1.0.1.dev6.dist-info/RECORD
